{"disqus":{"path":"/posts/2008-07-15-a-c-library-to-write-functional-code-part-v-the-match-operator/","commentCount":3,"comments":[{"postId":"4303143379","parentPostId":null,"date":"2008-07-15T05:50:34Z","author":"Luca Bolognese's WebLog : A C#","avatar":"","message":"<p>PingBack from <a href=\"http://blogs.msdn.com/lucabol/archive/2008/06/06/a-c-library-to-write-functional-code-part-iv-type-unions.aspx\" rel=\"nofollow noopener\" title=\"http://blogs.msdn.com/lucabol/archive/2008/06/06/a-c-library-to-write-functional-code-part-iv-type-unions.aspx\">http://blogs.msdn.com/lucabol/archive/2008/06/06/a-c-library-to-write-functional-code-part-iv-type-unions.aspx</a></p>","replies":[]},{"postId":"4303143383","parentPostId":null,"date":"2008-07-25T11:04:09Z","author":"Ells","avatar":"","message":"<p>Clever Match operator. I would like to see more of F# Cool</p>","replies":[]},{"postId":"4303143384","parentPostId":null,"date":"2008-07-31T10:24:41Z","author":"excel","avatar":"","message":"<p>linq is sexual perversion about programming and programmer, but this example is realy crazzy. U better using lisp it's have more facilities fo your perversion.</p>","replies":[]}]}}